.DS_Store
mlvizlib/__init__.py
mlvizlib/mlvizlib.py
mlvizlib/version.py
mlvizlib/classification/__init__.py
mlvizlib/classification/_confusion_matrix.py
mlvizlib/classification/viz_confusion_matrix.py
mlvizlib/utils/__init__.py
mlvizlib/utils/_input_validation.py
mlvizlib/utils/input_transformation.py
mlvizlib/utils/input_validation.py
mlvizlib-0.1.3.dist-info/AUTHORS.rst
mlvizlib-0.1.3.dist-info/LICENSE
mlvizlib-0.1.3.dist-info/METADATA
mlvizlib-0.1.3.dist-info/WHEEL
mlvizlib-0.1.3.dist-info/top_level.txt
mlvizlib-0.1.3.dist-info/RECORD
