Metadata-Version: 2.1
Name: mlvizlib
Version: 0.1.3
Summary: MLVizLib is a powerful package for generating quick, insightful, and stylish visualizations for machine learning.
Home-page: https://github.com/kristianbonnici/mlvizlib
Author: Kristian Bonnici
Author-email: kristiandaaniel@gmail.com
License: MIT license
Keywords: mlvizlib
Platform: UNKNOWN
Classifier: Development Status :: 2 - Pre-Alpha
Classifier: Intended Audience :: Developers
Classifier: License :: OSI Approved :: MIT License
Classifier: Natural Language :: English
Classifier: Programming Language :: Python :: 3
Classifier: Programming Language :: Python :: 3.6
Classifier: Programming Language :: Python :: 3.7
Classifier: Programming Language :: Python :: 3.8
Requires-Python: >=3.6
Requires-Dist: pytest
Requires-Dist: matplotlib
Requires-Dist: setuptools
Requires-Dist: numpy
Requires-Dist: pandas
